{"is_source_file": true, "format": "Dart", "description": "This file defines two reusable Flutter widgets: LoadingView and ErrorView, used for displaying loading indicators and error messages respectively.", "external_files": ["package:flutter/material.dart"], "external_methods": [], "published": ["LoadingView", "ErrorView"], "classes": [{"name": "LoadingView", "description": "A stateless widget that displays a centered loading indicator with an optional message."}, {"name": "ErrorView", "description": "A stateless widget that displays an error message with an optional retry button."}], "methods": [{"name": "build", "description": "Builds the UI for LoadingView and ErrorView widgets."}], "calls": ["Center", "Column", "CircularProgressIndicator", "SizedBox", "Text", "ElevatedButton"], "search-terms": ["LoadingView", "ErrorView", "Flutter widgets", "loading indicator", "error message", "common.dart"], "state": 2, "file_id": 17, "knowledge_revision": 35, "git_revision": "", "hash": "78b5e98e4a7be91ae36898333f2abffa", "format-version": 4, "code-base-name": "MobileApplication", "filename": "MobileApplication/lib/widgets/common.dart", "revision_history": [{"35": ""}]}